spannery/__init__.py
spannery/exceptions.py
spannery/fields.py
spannery/model.py
spannery/query.py
spannery/session.py
spannery/utils.py
spannery-0.2.2.dist-info/licenses/LICENSE
spannery-0.2.2.dist-info/METADATA
spannery-0.2.2.dist-info/WHEEL
spannery-0.2.2.dist-info/top_level.txt
spannery-0.2.2.dist-info/RECORD
