Metadata-Version: 2.4
Name: spannery
Version: 0.2.2
Summary: A lightweight ORM for Google Cloud Spanner(Sorcer)y 🧙
Author-email: Caio Pizzol <caio@harbourshare.com>
Classifier: Development Status :: 3 - Alpha
Classifier: Intended Audience :: Developers
Classifier: Programming Language :: Python :: 3
Classifier: Programming Language :: Python :: 3.10
Classifier: Programming Language :: Python :: 3.11
Classifier: Programming Language :: Python :: 3.12
Requires-Python: >=3.10
License-File: LICENSE
Requires-Dist: google-cloud-spanner>=3.0.0
Dynamic: license-file
